MANIFEST.in
README.rst
setup.py
pycodeobject/__init__.py
pycodeobject.egg-info/PKG-INFO
pycodeobject.egg-info/SOURCES.txt
pycodeobject.egg-info/dependency_links.txt
pycodeobject.egg-info/top_level.txt
pycodeobject/test/__init__.py
pycodeobject/test/pyc_zipper_bz2.py
pycodeobject/test/pyc_zipper_lzma.py
pycodeobject/test/pyc_zipper_zlib.py
pycodeobject/test/pyc_zipper_仅保护字节码.py
pycodeobject/test/pyc_zipper_处理目录.py
pycodeobject/test/pyc_zipper_脱壳.py
pycodeobject/test/test.pyc
pycodeobject/test/testcode.py