Metadata-Version: 1.1
Name: pycodeobject
Version: 1.0.5
Summary: 用于解析、编辑和处理Python字节码(bytecode)的工具。A tool for parsing and processing Python bytecode object.
Home-page: https://github.com/qfcy/Python/blob/main/pyobject/code_.py
Author: qfcy qq:3076711200
Author-email: 3076711200@qq.com
License: UNKNOWN
Keywords: python,bytecode,字节码,assembly,pyc,decompiling,反编译
Platform: UNKNOWN
Classifier: Topic :: Software Development :: Libraries :: Python Modules
Classifier: Programming Language :: Python :: 3
Classifier: Natural Language :: Chinese (Simplified)
Classifier: Topic :: Software Development :: Assemblers
Classifier: Topic :: Software Development :: Build Tools
Classifier: Topic :: Software Development :: Disassemblers
Classifier: Topic :: Software Development :: Bug Tracking
Classifier: Topic :: Utilities
Requires-Dist: pyobject
